setup.py
bhuvan_probability/Binomialdistribution.py
bhuvan_probability/Gaussiandistribution.py
bhuvan_probability/Generaldistribution.py
bhuvan_probability/__init__.py
bhuvan_probability.egg-info/PKG-INFO
bhuvan_probability.egg-info/SOURCES.txt
bhuvan_probability.egg-info/dependency_links.txt
bhuvan_probability.egg-info/not-zip-safe
bhuvan_probability.egg-info/top_level.txt