Metadata-Version: 1.0
Name: bhuvan-probability
Version: 1.1
Summary: Gaussian  and Binomial distributions
Home-page: UNKNOWN
Author: Gangadhar Bhuvan
Author-email: gangadharbhuvan1@gmail.com
License: UNKNOWN
Platform: UNKNOWN
